permoize/__init__.py
permoize/core.py
permoize-0.1.0.dist-info/DESCRIPTION.rst
permoize-0.1.0.dist-info/LICENSE.txt
permoize-0.1.0.dist-info/METADATA
permoize-0.1.0.dist-info/RECORD
permoize-0.1.0.dist-info/WHEEL
permoize-0.1.0.dist-info/metadata.json
permoize-0.1.0.dist-info/top_level.txt
