Metadata-Version: 2.0
Name: permoize
Version: 0.1.0
Summary: A persistent memoization library for Python
Home-page: https://github.com/idmit/permoize
Author: Ivan Dmitrievsky
Author-email: ivan.dmitrievsky+python@gmail.com
License: MIT License
Requires-Dist: diskcache
